PythonguruZhongwenXilieJiaochengChuyiFix1/README.md
PythonguruZhongwenXilieJiaochengChuyiFix1/__init__.py
PythonguruZhongwenXilieJiaochengChuyiFix1/__main__.py
PythonguruZhongwenXilieJiaochengChuyiFix1/file.epub
PythonguruZhongwenXilieJiaochengChuyiFix1/index.html
PythonguruZhongwenXilieJiaochengChuyiFix1/css/__init__.py
PythonguruZhongwenXilieJiaochengChuyiFix1/css/annotations.css
PythonguruZhongwenXilieJiaochengChuyiFix1/css/main.css
PythonguruZhongwenXilieJiaochengChuyiFix1/css/normalize.css
PythonguruZhongwenXilieJiaochengChuyiFix1/css/popup.css
PythonguruZhongwenXilieJiaochengChuyiFix1/font/__init__.py
PythonguruZhongwenXilieJiaochengChuyiFix1/font/fontello.eot
PythonguruZhongwenXilieJiaochengChuyiFix1/font/fontello.svg
PythonguruZhongwenXilieJiaochengChuyiFix1/font/fontello.ttf
PythonguruZhongwenXilieJiaochengChuyiFix1/font/fontello.woff
PythonguruZhongwenXilieJiaochengChuyiFix1/img/__init__.py
PythonguruZhongwenXilieJiaochengChuyiFix1/img/annotator-glyph-sprite.png
PythonguruZhongwenXilieJiaochengChuyiFix1/img/annotator-icon-sprite.png
PythonguruZhongwenXilieJiaochengChuyiFix1/img/apple-touch-icon.png
PythonguruZhongwenXilieJiaochengChuyiFix1/img/cancelfullscreen.png
PythonguruZhongwenXilieJiaochengChuyiFix1/img/close.png
PythonguruZhongwenXilieJiaochengChuyiFix1/img/fullscreen.png
PythonguruZhongwenXilieJiaochengChuyiFix1/img/loader.gif
PythonguruZhongwenXilieJiaochengChuyiFix1/img/menu-icon.png
PythonguruZhongwenXilieJiaochengChuyiFix1/img/save.png
PythonguruZhongwenXilieJiaochengChuyiFix1/img/saved.png
PythonguruZhongwenXilieJiaochengChuyiFix1/img/settings-s.png
PythonguruZhongwenXilieJiaochengChuyiFix1/img/settings.png
PythonguruZhongwenXilieJiaochengChuyiFix1/img/star.png
PythonguruZhongwenXilieJiaochengChuyiFix1/js/__init__.py
PythonguruZhongwenXilieJiaochengChuyiFix1/js/epub.js
PythonguruZhongwenXilieJiaochengChuyiFix1/js/epub.min.js
PythonguruZhongwenXilieJiaochengChuyiFix1/js/epub.min.map
PythonguruZhongwenXilieJiaochengChuyiFix1/js/hooks.min.js
pythonguru_zhongwen_xilie_jiaocheng_chuyi_fix1-2025.3.24.0.dist-info/METADATA
pythonguru_zhongwen_xilie_jiaocheng_chuyi_fix1-2025.3.24.0.dist-info/WHEEL
pythonguru_zhongwen_xilie_jiaocheng_chuyi_fix1-2025.3.24.0.dist-info/entry_points.txt
pythonguru_zhongwen_xilie_jiaocheng_chuyi_fix1-2025.3.24.0.dist-info/top_level.txt
pythonguru_zhongwen_xilie_jiaocheng_chuyi_fix1-2025.3.24.0.dist-info/RECORD
